funcnodes_rdkit/__init__.py
funcnodes_rdkit/mol.py
funcnodes_rdkit/react_plugin/css/jquery-ui-1.11.4.css
funcnodes_rdkit/react_plugin/js/ChemDoodleWeb.js
funcnodes_rdkit/react_plugin/js/main.js
funcnodes_rdkit/svg.py
funcnodes_rdkit-0.1.3.dist-info/entry_points.txt
funcnodes_rdkit-0.1.3.dist-info/LICENSE
funcnodes_rdkit-0.1.3.dist-info/METADATA
funcnodes_rdkit-0.1.3.dist-info/WHEEL
funcnodes_rdkit-0.1.3.dist-info/RECORD
