Metadata-Version: 2.1
Name: funcnodes-rdkit
Version: 0.1.3
Summary: rdkit for funcnodes
License: AGPL-3.0
Author: Julian Kimmig
Author-email: julian.kimmig@gmx.net
Requires-Python: >=3.11
Classifier: License :: OSI Approved :: GNU Affero General Public License v3
Classifier: Programming Language :: Python :: 3
Classifier: Programming Language :: Python :: 3.11
Classifier: Programming Language :: Python :: 3.12
Requires-Dist: funcnodes
Requires-Dist: rdkit
